elodie/__init__.py
elodie/compatability.py
elodie/config.py
elodie/constants.py
elodie/dependencies.py
elodie/elodie.py
elodie/filesystem.py
elodie/geolocation.py
elodie/localstorage.py
elodie/log.py
elodie/result.py
elodie-0.0.1b0.dist-info/LICENSE
elodie-0.0.1b0.dist-info/METADATA
elodie-0.0.1b0.dist-info/WHEEL
elodie-0.0.1b0.dist-info/entry_points.txt
elodie-0.0.1b0.dist-info/top_level.txt
elodie-0.0.1b0.dist-info/RECORD
