Metadata-Version: 2.1
Name: elodie
Version: 0.0.1b0
Summary: Your Personal EXIF-based Photo, Video and Audio Assistant
Home-page: https://github.com/jmathai/elodie
Author: Jaisen Mathai
Author-email: jaisen@jmathai.com
License: Apache 2.0
Keywords: photo organization photography
Platform: UNKNOWN
Classifier: License :: OSI Approved :: Apache Software License
Requires-Dist: click (==6.6)
Requires-Dist: requests (==2.20.0)
Requires-Dist: Send2Trash (==1.3.0)
Requires-Dist: future (==0.16.0)
Requires-Dist: configparser (==3.5.0)
Requires-Dist: tabulate (==0.7.7)
Requires-Dist: Pillow (==5.3.0)
